gitign-0.18.dist-info/licenses/LICENSE
gitignore/gitignore.py
gitign-0.18.dist-info/METADATA
gitign-0.18.dist-info/WHEEL
gitign-0.18.dist-info/entry_points.txt
gitign-0.18.dist-info/top_level.txt
gitign-0.18.dist-info/RECORD
