Metadata-Version: 2.4
Name: gitign
Version: 0.18
Summary: A powerful and user-friendly Python script to generate `.gitignore` files with default entries, custom patterns, or templates from gitignore.io
Home-page: https://github.com/cumulus13/gitignore
Author: Hadi Cahyadi
Author-email: cumulus13@gmail.com
License: MIT
Project-URL: Bug Tracker, https://github.com/cumulus13/gitignore/issues
Keywords: gitignore gitignore.io rich terminal
Classifier: Programming Language :: Python :: 3
Classifier: License :: OSI Approved :: MIT License
Classifier: Operating System :: OS Independent
Requires-Python: >=3.6
License-File: LICENSE
Requires-Dist: rich>=10.0.0
Requires-Dist: licface
Requires-Dist: rich_argparse
Dynamic: author
Dynamic: author-email
Dynamic: classifier
Dynamic: description
Dynamic: description-content-type
Dynamic: home-page
Dynamic: keywords
Dynamic: license
Dynamic: license-file
Dynamic: project-url
Dynamic: requires-dist
Dynamic: requires-python
Dynamic: summary
